rsyslog_pseudonymizer/__init__.py
rsyslog_pseudonymizer/rsyslog_pseudonymizer.py
rsyslog_pseudonymizer/pseudonymizer/DisassembleResult.py
rsyslog_pseudonymizer/pseudonymizer/Disassembler.py
rsyslog_pseudonymizer/pseudonymizer/DomainPseudonymizer.py
rsyslog_pseudonymizer/pseudonymizer/EmailPseudonymizer.py
rsyslog_pseudonymizer/pseudonymizer/HierarchicalPseudonymDataGenerator.py
rsyslog_pseudonymizer/pseudonymizer/IPv4Pseudonymizer.py
rsyslog_pseudonymizer/pseudonymizer/IPv6Pseudonymizer.py
rsyslog_pseudonymizer/pseudonymizer/IdentityDisassembler.py
rsyslog_pseudonymizer/pseudonymizer/IncrementingPseudonymDataGenerator.py
rsyslog_pseudonymizer/pseudonymizer/MatrixIDPseudonymizer.py
rsyslog_pseudonymizer/pseudonymizer/PseudonymData.py
rsyslog_pseudonymizer/pseudonymizer/PseudonymDataGenerator.py
rsyslog_pseudonymizer/pseudonymizer/PseudonymReplacer.py
rsyslog_pseudonymizer/pseudonymizer/PseudonymizeResult.py
rsyslog_pseudonymizer/pseudonymizer/Pseudonymizer.py
rsyslog_pseudonymizer/pseudonymizer/Reassembler.py
rsyslog_pseudonymizer/pseudonymizer/UsernameDomainPseudonymDataGenerator.py
rsyslog_pseudonymizer/pseudonymizer/UsernamePseudonymizer.py
rsyslog_pseudonymizer/pseudonymizer/__init__.py
rsyslog_pseudonymizer/pseudonymizer/pseudonym_generator.py
rsyslog_pseudonymizer-1.0.2.dist-info/COPYING.ASL20
rsyslog_pseudonymizer-1.0.2.dist-info/METADATA
rsyslog_pseudonymizer-1.0.2.dist-info/WHEEL
rsyslog_pseudonymizer-1.0.2.dist-info/entry_points.txt
rsyslog_pseudonymizer-1.0.2.dist-info/top_level.txt
rsyslog_pseudonymizer-1.0.2.dist-info/RECORD
