Metadata-Version: 2.1
Name: rsyslog-pseudonymizer
Version: 1.0.2
Summary: RsyslogPseudonymizer is a plug-in module for Rsyslog based on Python which replaces personal identifiers in log messages by pseudonyms before they are written to log files. The pseudonym-mapping is only kept in RAM.
Home-page: https://framagit.org/iflog/rsyslog_pseudonymizer
Author: iflog
Author-email: qiensamw@runbox.com
Maintainer: iflog
Maintainer-email: qiensamw@runbox.com
License: Apache-2.0
Platform: UNKNOWN
Classifier: Development Status :: 4 - Beta
Classifier: Intended Audience :: System Administrators
Classifier: License :: OSI Approved :: Apache Software License
Classifier: Natural Language :: English
Classifier: Operating System :: POSIX
Classifier: Programming Language :: Python :: 3.6
Requires-Dist: tld (<1,>=0.9.2)
Provides-Extra: dev
Requires-Dist: hatch ; extra == 'dev'
Requires-Dist: tox ; extra == 'dev'
Requires-Dist: coverage ; extra == 'dev'
Requires-Dist: pytest ; extra == 'dev'
Provides-Extra: test
Requires-Dist: coverage ; extra == 'test'
Requires-Dist: pytest ; extra == 'test'
